TermTk/__init__.py
TermTk/TTkAbstract/__init__.py
TermTk/TTkAbstract/abstractitemmodel.py
TermTk/TTkAbstract/abstractscrollarea.py
TermTk/TTkAbstract/abstractscrollview.py
TermTk/TTkAbstract/abstracttablemodel.py
TermTk/TTkCore/__init__.py
TermTk/TTkCore/canvas.py
TermTk/TTkCore/cfg.py
TermTk/TTkCore/color.py
TermTk/TTkCore/constant.py
TermTk/TTkCore/filebuffer.py
TermTk/TTkCore/helper.py
TermTk/TTkCore/log.py
TermTk/TTkCore/propertyanimation.py
TermTk/TTkCore/shortcut.py
TermTk/TTkCore/signal.py
TermTk/TTkCore/string.py
TermTk/TTkCore/timer.py
TermTk/TTkCore/timer_interface.py
TermTk/TTkCore/timer_pyodide.py
TermTk/TTkCore/timer_unix.py
TermTk/TTkCore/ttk.py
TermTk/TTkCore/util.py
TermTk/TTkCore/TTkTerm/__init__.py
TermTk/TTkCore/TTkTerm/colors.py
TermTk/TTkCore/TTkTerm/colors_ansi_map.py
TermTk/TTkCore/TTkTerm/input.py
TermTk/TTkCore/TTkTerm/input_mono.py
TermTk/TTkCore/TTkTerm/input_thread.py
TermTk/TTkCore/TTkTerm/inputkey.py
TermTk/TTkCore/TTkTerm/inputmouse.py
TermTk/TTkCore/TTkTerm/term.py
TermTk/TTkCore/TTkTerm/term_base.py
TermTk/TTkCore/drivers/__init__.py
TermTk/TTkCore/drivers/_unused_.unix_thread.py
TermTk/TTkCore/drivers/pyodide.py
TermTk/TTkCore/drivers/term_pyodide.py
TermTk/TTkCore/drivers/term_unix_common.py
TermTk/TTkCore/drivers/term_unix_darwin.py
TermTk/TTkCore/drivers/term_unix_linux.py
TermTk/TTkCore/drivers/term_unix_serial.py
TermTk/TTkCore/drivers/term_windows.py
TermTk/TTkCore/drivers/unix.py
TermTk/TTkCore/drivers/unix_gpm.py
TermTk/TTkCore/drivers/windows.py
TermTk/TTkCrossTools/__init__.py
TermTk/TTkCrossTools/savetools.py
TermTk/TTkGui/__init__.py
TermTk/TTkGui/clipboard.py
TermTk/TTkGui/drag.py
TermTk/TTkGui/textcursor.py
TermTk/TTkGui/textdocument.py
TermTk/TTkGui/textdocument_highlight.py
TermTk/TTkGui/textdocument_highlight_pygments.py
TermTk/TTkGui/textwrap1.py
TermTk/TTkGui/tooltip.py
TermTk/TTkLayouts/__init__.py
TermTk/TTkLayouts/boxlayout.py
TermTk/TTkLayouts/gridlayout.py
TermTk/TTkLayouts/layout.py
pytermtk-0.49.0a0.dist-info/METADATA
pytermtk-0.49.0a0.dist-info/WHEEL
pytermtk-0.49.0a0.dist-info/top_level.txt
pytermtk-0.49.0a0.dist-info/RECORD
