Metadata-Version: 2.4
Name: pyTermTk
Version: 0.49.0a0
Summary: Python Terminal Toolkit
Author-email: Eugenio Parodi <ceccopierangiolieugenio@googlemail.com>
License: MIT License
Project-URL: Homepage, https://github.com/ceccopierangiolieugenio/pyTermTk
Project-URL: Documentation, https://ceccopierangiolieugenio.github.io/pyTermTk-Docs/
Project-URL: Repository, https://github.com/ceccopierangiolieugenio/pyTermTk.git
Project-URL: Issues, https://github.com/ceccopierangiolieugenio/pyTermTk/issues
Project-URL: Changelog, https://github.com/ceccopierangiolieugenio/pyTermTk/blob/main/libs/pyTermTk/CHANGELOG.md
Classifier: Programming Language :: Python :: 3
Classifier: License :: OSI Approved :: MIT License
Classifier: Operating System :: OS Independent
Classifier: Development Status :: 3 - Alpha
Classifier: Environment :: Console
Classifier: Intended Audience :: Education
Classifier: Intended Audience :: Developers
Classifier: Intended Audience :: Information Technology
Classifier: Topic :: Terminals
Classifier: Topic :: Text Editors :: Text Processing
Classifier: Topic :: Software Development :: User Interfaces
Classifier: Topic :: Software Development :: Libraries
Classifier: Topic :: Software Development :: Libraries :: Python Modules
Classifier: Topic :: Software Development :: Libraries :: Application Frameworks
Requires-Python: >=3.9
Provides-Extra: test
Requires-Dist: pytest>=8.3.4; extra == "test"
Requires-Dist: flake8>=7.2.0; extra == "test"
Requires-Dist: mypy>=1.15.0; extra == "test"
